pytest_abstracts/__init__.py
pytest_abstracts/py.typed
pytest_abstracts-0.0.4.dist-info/METADATA
pytest_abstracts-0.0.4.dist-info/WHEEL
pytest_abstracts-0.0.4.dist-info/entry_points.txt
pytest_abstracts-0.0.4.dist-info/namespace_packages.txt
pytest_abstracts-0.0.4.dist-info/top_level.txt
pytest_abstracts-0.0.4.dist-info/RECORD
