Metadata-Version: 2.1
Name: pytest-abstracts
Version: 0.0.4
Summary: A contextmanager pytest fixture for handling multiple mock abstracts
Home-page: https://github.com/envoyproxy/pytooling/tree/main/pytest-abstracts
Author: Ryan Northey
Author-email: ryan@synca.io
Maintainer: Ryan Northey
Maintainer-email: ryan@synca.io
License: Apache Software License 2.0
Platform: UNKNOWN
Requires-Dist: abstracts (>=0.0.12)
